ScrapyProxyCompat/ScrapyProxyCompat.py
ScrapyProxyCompat/__init__.py
ScrapyProxyCompat-0.1.4.dist-info/LICENSE
ScrapyProxyCompat-0.1.4.dist-info/METADATA
ScrapyProxyCompat-0.1.4.dist-info/WHEEL
ScrapyProxyCompat-0.1.4.dist-info/top_level.txt
ScrapyProxyCompat-0.1.4.dist-info/RECORD
