Metadata-Version: 2.1
Name: ScrapyProxyCompat
Version: 0.1.4
Summary: A module to wrap PProxy and allow more proxy options in Scrapy
Home-page: https://github.com/elihopk/ScrapyProxyCompat
Author: Eli Hopkins
Author-email: ewh3157@rit.edu
License: UNKNOWN
Project-URL: Bug Tracker, https://github.com/elihopk/ScrapyProxyCompat/issues
Platform: UNKNOWN
Classifier: Programming Language :: Python :: 3
Classifier: License :: OSI Approved :: MIT License
Classifier: Operating System :: OS Independent
Requires-Python: >=3.6
License-File: LICENSE
